crimson/git_loader/__init__.py
crimson/git_loader/loader.py
crimson/git_loader/reader.py
crimson/git_loader/structure.py
crimson_git_loader-0.1.1.dist-info/LICENSE
crimson_git_loader-0.1.1.dist-info/METADATA
crimson_git_loader-0.1.1.dist-info/WHEEL
crimson_git_loader-0.1.1.dist-info/top_level.txt
crimson_git_loader-0.1.1.dist-info/RECORD
