Metadata-Version: 2.1
Name: crimson-git-loader
Version: 0.1.1
Summary: Simplify downloading certain files or folders from git repositories.
Author-email: Sisung Kim <sisung.kim1@gmail.com>
Project-URL: Homepage, https://github.com/crimson206/git-loader
Project-URL: Bug Tracker, https://github.com/crimson206/git-loader/issues
Classifier: Programming Language :: Python :: 3
Classifier: Intended Audience :: Developers
Classifier: Topic :: Software Development :: Build Tools
Classifier: License :: OSI Approved :: MIT License
Classifier: Operating System :: OS Independent
Requires-Python: >=3.9
License-File: LICENSE
Requires-Dist: pydantic
Requires-Dist: requests
Requires-Dist: crimson-file-loader==0.1.3
